[
    {
        "image_url": "\"https://inaturalist-open-data.s3.amazonaws.com/photos/341020627/medium.jpg\"",
        "name": "Genus Cystodinium"
    },
    {
        "image_url": "\"https://inaturalist-open-data.s3.amazonaws.com/photos/330358076/medium.jpg\"",
        "name": "Genus Cystodinium"
    },
    {
        "image_url": "\"https://inaturalist-open-data.s3.amazonaws.com/photos/304104676/medium.png\"",
        "name": "Genus Cystodinium"
    },
    {
        "image_url": "\"https://inaturalist-open-data.s3.amazonaws.com/photos/296822794/medium.jpeg\"",
        "name": "Cystodinium bataviense"
    },
    {
        "image_url": "\"https://inaturalist-open-data.s3.amazonaws.com/photos/277483401/medium.jpeg\"",
        "name": "Genus Cystodinium"
    },
    {
        "image_url": "\"https://static.inaturalist.org/photos/262369806/medium.jpeg\"",
        "name": "Cystodinium cornifax"
    },
    {
        "image_url": "\"https://inaturalist-open-data.s3.amazonaws.com/photos/231760754/medium.png\"",
        "name": "Cystodinium cornifax"
    },
    {
        "image_url": "\"https://inaturalist-open-data.s3.amazonaws.com/photos/227968095/medium.jpg\"",
        "name": "Cystodinium bataviense"
    },
    {
        "image_url": "\"https://inaturalist-open-data.s3.amazonaws.com/photos/171729121/medium.jpg\"",
        "name": "Cystodinium bataviense"
    },
    {
        "image_url": "\"https://static.inaturalist.org/photos/166160955/medium.jpg\"",
        "name": "Cystodinium cornifax"
    },
    {
        "image_url": "\"https://static.inaturalist.org/photos/166104522/medium.jpg\"",
        "name": "Cystodinium cornifax"
    },
    {
        "image_url": "\"https://static.inaturalist.org/photos/154727599/medium.jpeg\"",
        "name": "Genus Cystodinium"
    },
    {
        "image_url": "\"https://inaturalist-open-data.s3.amazonaws.com/photos/142488240/medium.jpg\"",
        "name": "Cystodinium cornifax"
    },
    {
        "image_url": "\"https://inaturalist-open-data.s3.amazonaws.com/photos/105723102/medium.jpg\"",
        "name": "Cystodinium cornifax"
    },
    {
        "image_url": "\"https://inaturalist-open-data.s3.amazonaws.com/photos/48934679/medium.jpeg\"",
        "name": "Genus Cystodinium"
    },
    {
        "image_url": "\"https://inaturalist-open-data.s3.amazonaws.com/photos/44611787/medium.jpg\"",
        "name": "Genus Cystodinium"
    },
    {
        "image_url": "\"https://inaturalist-open-data.s3.amazonaws.com/photos/22493542/medium.jpeg\"",
        "name": "Genus Cystodinium"
    },
    {
        "image_url": "\"https://inaturalist-open-data.s3.amazonaws.com/photos/3921496/medium.jpg\"",
        "name": "Cystodinium bataviense"
    }
]